headloop/__init__.py
headloop/designer.py
headloop-1.0.11.dist-info/LICENSE
headloop-1.0.11.dist-info/METADATA
headloop-1.0.11.dist-info/WHEEL
headloop-1.0.11.dist-info/top_level.txt
headloop-1.0.11.dist-info/RECORD
