Metadata-Version: 2.1
Name: headloop
Version: 1.0.11
Summary: Package for designing headloop primers to use in headloop suppression PCR to suppress amplification of a known haplotype.
Home-page: https://github.com/GTPowell21/Headloop
Author: Gareth T. Powell
Author-email: g.powell@ucl.ac.uk
License: GPLv3
Platform: UNKNOWN
Classifier: Programming Language :: Python :: 3
Classifier: License :: OSI Approved :: GNU General Public License v3 (GPLv3)
Classifier: Operating System :: OS Independent
Classifier: Intended Audience :: Science/Research
Requires-Python: >=3.6
Requires-Dist: melt (>=1.0.3)
Requires-Dist: biopython (>=1.77)
